topenai/__init__.py
topenai-0.0.8.dist-info/LICENSE
topenai-0.0.8.dist-info/METADATA
topenai-0.0.8.dist-info/WHEEL
topenai-0.0.8.dist-info/entry_points.txt
topenai-0.0.8.dist-info/top_level.txt
topenai-0.0.8.dist-info/RECORD
