Metadata-Version: 2.1
Name: topenai
Version: 0.0.8
Summary: CLI tool to chat with OpenAI GPT
Home-page: https://github.com/vladzima/topenai
Author: vladzima
Author-email: v.o.arbatov@gmail.com
Classifier: Programming Language :: Python
Classifier: Operating System :: OS Independent
License-File: LICENSE
